LICENSE
MANIFEST.in
README.rst
dynamictop.py
setup.py
dynamictop.egg-info/PKG-INFO
dynamictop.egg-info/SOURCES.txt
dynamictop.egg-info/dependency_links.txt
dynamictop.egg-info/not-zip-safe
dynamictop.egg-info/requires.txt
dynamictop.egg-info/top_level.txt