Metadata-Version: 1.1
Name: dynamictop
Version: 0.1.0
Summary: Tools for creating a dynamic top file
Home-page: https://github.com/virtru/dynamictop
Author: Reuven V. Gonzales
Author-email: reuven@virtru.com
License: MIT
Platform: *nix
Classifier: License :: OSI Approved :: MIT License
Classifier: Intended Audience :: Developers
Classifier: Programming Language :: Python
Classifier: Operating System :: POSIX
Classifier: Topic :: Software Development :: Build Tools
